[{"display_html":"<span class=\"keyword\">data</span> <a href=\"#t:Prod\">Prod</a> :: (k -&gt; <a href=\"../base-4.12.0.0/Data-Kind.html#t:Type\" title=\"Data.Kind\">Type</a>) -&gt; [k] -&gt; <a href=\"../base-4.12.0.0/Data-Kind.html#t:Type\" title=\"Data.Kind\">Type</a> <span class=\"keyword\">where</span><ul class=\"subs\"><li><a href=\"#v:-216-\">&#216;</a> :: <a href=\"Data-Type-List-Prod.html#t:Prod\" title=\"Data.Type.List.Prod\">Prod</a> f '[]</li><li><a href=\"#v::-60-\">(:&lt;)</a> :: f a -&gt; <a href=\"Data-Type-List-Prod.html#t:Prod\" title=\"Data.Type.List.Prod\">Prod</a> f as -&gt; <a href=\"Data-Type-List-Prod.html#t:Prod\" title=\"Data.Type.List.Prod\">Prod</a> f (a ': as)</li></ul>","name":"Prod :< Ø","module":"Data.Type.List.Prod","link":"Data-Type-List-Prod.html#t:Prod"},{"display_html":"<a href=\"#v:pNil\">pNil</a> :: <a href=\"Data-Type-List-Prod.html#t:Prod\" title=\"Data.Type.List.Prod\">Prod</a> f '[]","name":"pNil","module":"Data.Type.List.Prod","link":"Data-Type-List-Prod.html#v:pNil"},{"display_html":"<a href=\"#v:indexProd\">indexProd</a> :: <a href=\"../decidable-0.1.4.0/Data-Type-Universe.html#t:Index\" title=\"Data.Type.Universe\">Index</a> as x -&gt; <a href=\"Data-Type-List-Prod.html#t:Prod\" title=\"Data.Type.List.Prod\">Prod</a> f as -&gt; f x","name":"indexProd","module":"Data.Type.List.Prod","link":"Data-Type-List-Prod.html#v:indexProd"},{"display_html":"<a href=\"#v:lensProd-39-\">lensProd'</a> :: <span class=\"keyword\">forall</span> as x g f. <a href=\"../base-4.12.0.0/Data-Functor.html#t:Functor\" title=\"Data.Functor\">Functor</a> f =&gt; <a href=\"../decidable-0.1.4.0/Data-Type-Universe.html#t:Index\" title=\"Data.Type.Universe\">Index</a> as x -&gt; (g x -&gt; f (g x)) -&gt; <a href=\"Data-Type-List-Prod.html#t:Prod\" title=\"Data.Type.List.Prod\">Prod</a> g as -&gt; f (<a href=\"Data-Type-List-Prod.html#t:Prod\" title=\"Data.Type.List.Prod\">Prod</a> g as)","name":"lensProd'","module":"Data.Type.List.Prod","link":"Data-Type-List-Prod.html#v:lensProd-39-"},{"display_html":"<a href=\"#v:headProd\">headProd</a> :: <a href=\"Data-Type-List-Prod.html#t:Prod\" title=\"Data.Type.List.Prod\">Prod</a> f (a ': as) -&gt; f a","name":"headProd","module":"Data.Type.List.Prod","link":"Data-Type-List-Prod.html#v:headProd"},{"display_html":"<a href=\"#v:tailProd\">tailProd</a> :: <a href=\"Data-Type-List-Prod.html#t:Prod\" title=\"Data.Type.List.Prod\">Prod</a> f (a ': as) -&gt; <a href=\"Data-Type-List-Prod.html#t:Prod\" title=\"Data.Type.List.Prod\">Prod</a> f as","name":"tailProd","module":"Data.Type.List.Prod","link":"Data-Type-List-Prod.html#v:tailProd"},{"display_html":"<span class=\"keyword\">data</span> <a href=\"#t:Insert\">Insert</a> :: [k] -&gt; [k] -&gt; k -&gt; <a href=\"../base-4.12.0.0/Data-Kind.html#t:Type\" title=\"Data.Kind\">Type</a> <span class=\"keyword\">where</span><ul class=\"subs\"><li><a href=\"#v:InsZ\">InsZ</a> :: <a href=\"Data-Type-List-Edit.html#t:Insert\" title=\"Data.Type.List.Edit\">Insert</a> as (x ': as) x</li><li><a href=\"#v:InsS\">InsS</a> :: <a href=\"Data-Type-List-Edit.html#t:Insert\" title=\"Data.Type.List.Edit\">Insert</a> as bs x -&gt; <a href=\"Data-Type-List-Edit.html#t:Insert\" title=\"Data.Type.List.Edit\">Insert</a> (a ': as) (a ': bs) x</li></ul>","name":"Insert InsZ InsS","module":"Data.Type.List.Edit","link":"Data-Type-List-Edit.html#t:Insert"},{"display_html":"<span class=\"keyword\">data</span> <a href=\"#t:Delete\">Delete</a> :: [k] -&gt; [k] -&gt; k -&gt; <a href=\"../base-4.12.0.0/Data-Kind.html#t:Type\" title=\"Data.Kind\">Type</a> <span class=\"keyword\">where</span><ul class=\"subs\"><li><a href=\"#v:DelZ\">DelZ</a> :: <a href=\"Data-Type-List-Edit.html#t:Delete\" title=\"Data.Type.List.Edit\">Delete</a> (x ': as) as x</li><li><a href=\"#v:DelS\">DelS</a> :: <a href=\"Data-Type-List-Edit.html#t:Delete\" title=\"Data.Type.List.Edit\">Delete</a> as bs x -&gt; <a href=\"Data-Type-List-Edit.html#t:Delete\" title=\"Data.Type.List.Edit\">Delete</a> (a ': as) (a ': bs) x</li></ul>","name":"Delete DelZ DelS","module":"Data.Type.List.Edit","link":"Data-Type-List-Edit.html#t:Delete"},{"display_html":"<a href=\"#v:insToDel\">insToDel</a> :: <a href=\"Data-Type-List-Edit.html#t:Insert\" title=\"Data.Type.List.Edit\">Insert</a> as bs x -&gt; <a href=\"Data-Type-List-Edit.html#t:Delete\" title=\"Data.Type.List.Edit\">Delete</a> bs as x","name":"insToDel","module":"Data.Type.List.Edit","link":"Data-Type-List-Edit.html#v:insToDel"},{"display_html":"<a href=\"#v:delToIns\">delToIns</a> :: <a href=\"Data-Type-List-Edit.html#t:Delete\" title=\"Data.Type.List.Edit\">Delete</a> as bs x -&gt; <a href=\"Data-Type-List-Edit.html#t:Insert\" title=\"Data.Type.List.Edit\">Insert</a> bs as x","name":"delToIns","module":"Data.Type.List.Edit","link":"Data-Type-List-Edit.html#v:delToIns"},{"display_html":"<span class=\"keyword\">data</span> <a href=\"#t:Substitute\">Substitute</a> :: [k] -&gt; [k] -&gt; k -&gt; k -&gt; <a href=\"../base-4.12.0.0/Data-Kind.html#t:Type\" title=\"Data.Kind\">Type</a> <span class=\"keyword\">where</span><ul class=\"subs\"><li><a href=\"#v:SubZ\">SubZ</a> :: <a href=\"Data-Type-List-Edit.html#t:Substitute\" title=\"Data.Type.List.Edit\">Substitute</a> (x ': as) (y ': as) x y</li><li><a href=\"#v:SubS\">SubS</a> :: <a href=\"Data-Type-List-Edit.html#t:Substitute\" title=\"Data.Type.List.Edit\">Substitute</a> as bs x y -&gt; <a href=\"Data-Type-List-Edit.html#t:Substitute\" title=\"Data.Type.List.Edit\">Substitute</a> (c ': as) (c ': bs) x y</li></ul>","name":"Substitute SubZ SubS","module":"Data.Type.List.Edit","link":"Data-Type-List-Edit.html#t:Substitute"},{"display_html":"<a href=\"#v:flipSub\">flipSub</a> :: <a href=\"Data-Type-List-Edit.html#t:Substitute\" title=\"Data.Type.List.Edit\">Substitute</a> as bs x y -&gt; <a href=\"Data-Type-List-Edit.html#t:Substitute\" title=\"Data.Type.List.Edit\">Substitute</a> bs as y x","name":"flipSub","module":"Data.Type.List.Edit","link":"Data-Type-List-Edit.html#v:flipSub"},{"display_html":"<span class=\"keyword\">data</span> <a href=\"#t:Edit\">Edit</a> :: [k] -&gt; [k] -&gt; <a href=\"../base-4.12.0.0/Data-Kind.html#t:Type\" title=\"Data.Kind\">Type</a> <span class=\"keyword\">where</span><ul class=\"subs\"><li><a href=\"#v:ENil\">ENil</a> :: <a href=\"Data-Type-List-Edit.html#t:Edit\" title=\"Data.Type.List.Edit\">Edit</a> as as</li><li><a href=\"#v:EIns\">EIns</a> :: <a href=\"Data-Type-List-Edit.html#t:Insert\" title=\"Data.Type.List.Edit\">Insert</a> bs cs x -&gt; <a href=\"Data-Type-List-Edit.html#t:Edit\" title=\"Data.Type.List.Edit\">Edit</a> as bs -&gt; <a href=\"Data-Type-List-Edit.html#t:Edit\" title=\"Data.Type.List.Edit\">Edit</a> as cs</li><li><a href=\"#v:EDel\">EDel</a> :: <a href=\"Data-Type-List-Edit.html#t:Delete\" title=\"Data.Type.List.Edit\">Delete</a> bs cs x -&gt; <a href=\"Data-Type-List-Edit.html#t:Edit\" title=\"Data.Type.List.Edit\">Edit</a> as bs -&gt; <a href=\"Data-Type-List-Edit.html#t:Edit\" title=\"Data.Type.List.Edit\">Edit</a> as cs</li><li><a href=\"#v:ESub\">ESub</a> :: <a href=\"Data-Type-List-Edit.html#t:Substitute\" title=\"Data.Type.List.Edit\">Substitute</a> bs cs x y -&gt; <a href=\"Data-Type-List-Edit.html#t:Edit\" title=\"Data.Type.List.Edit\">Edit</a> as bs -&gt; <a href=\"Data-Type-List-Edit.html#t:Edit\" title=\"Data.Type.List.Edit\">Edit</a> as cs</li></ul>","name":"Edit ENil EIns EDel ESub","module":"Data.Type.List.Edit","link":"Data-Type-List-Edit.html#t:Edit"},{"display_html":"<a href=\"#v:flipEdit\">flipEdit</a> :: <a href=\"Data-Type-List-Edit.html#t:Edit\" title=\"Data.Type.List.Edit\">Edit</a> as bs -&gt; <a href=\"Data-Type-List-Edit.html#t:Edit\" title=\"Data.Type.List.Edit\">Edit</a> bs as","name":"flipEdit","module":"Data.Type.List.Edit","link":"Data-Type-List-Edit.html#v:flipEdit"},{"display_html":"<a href=\"#v:insertProd\">insertProd</a> :: <a href=\"Data-Type-List-Edit.html#t:Insert\" title=\"Data.Type.List.Edit\">Insert</a> as bs x -&gt; f x -&gt; <a href=\"Data-Type-List-Prod.html#t:Prod\" title=\"Data.Type.List.Prod\">Prod</a> f as -&gt; <a href=\"Data-Type-List-Prod.html#t:Prod\" title=\"Data.Type.List.Prod\">Prod</a> f bs","name":"insertProd","module":"Data.Type.List.Edit","link":"Data-Type-List-Edit.html#v:insertProd"},{"display_html":"<a href=\"#v:deleteProd\">deleteProd</a> :: <a href=\"Data-Type-List-Edit.html#t:Delete\" title=\"Data.Type.List.Edit\">Delete</a> as bs x -&gt; <a href=\"Data-Type-List-Prod.html#t:Prod\" title=\"Data.Type.List.Prod\">Prod</a> f as -&gt; <a href=\"Data-Type-List-Prod.html#t:Prod\" title=\"Data.Type.List.Prod\">Prod</a> f bs","name":"deleteProd","module":"Data.Type.List.Edit","link":"Data-Type-List-Edit.html#v:deleteProd"},{"display_html":"<a href=\"#v:deleteGetProd\">deleteGetProd</a> :: <a href=\"Data-Type-List-Edit.html#t:Delete\" title=\"Data.Type.List.Edit\">Delete</a> as bs x -&gt; <a href=\"Data-Type-List-Prod.html#t:Prod\" title=\"Data.Type.List.Prod\">Prod</a> f as -&gt; (f x, <a href=\"Data-Type-List-Prod.html#t:Prod\" title=\"Data.Type.List.Prod\">Prod</a> f bs)","name":"deleteGetProd","module":"Data.Type.List.Edit","link":"Data-Type-List-Edit.html#v:deleteGetProd"},{"display_html":"<a href=\"#v:lensProd\">lensProd</a> :: <span class=\"keyword\">forall</span> as bs x y g f. <a href=\"../base-4.12.0.0/Data-Functor.html#t:Functor\" title=\"Data.Functor\">Functor</a> f =&gt; <a href=\"Data-Type-List-Edit.html#t:Substitute\" title=\"Data.Type.List.Edit\">Substitute</a> as bs x y -&gt; (g x -&gt; f (g y)) -&gt; <a href=\"Data-Type-List-Prod.html#t:Prod\" title=\"Data.Type.List.Prod\">Prod</a> g as -&gt; f (<a href=\"Data-Type-List-Prod.html#t:Prod\" title=\"Data.Type.List.Prod\">Prod</a> g bs)","name":"lensProd","module":"Data.Type.List.Edit","link":"Data-Type-List-Edit.html#v:lensProd"},{"display_html":"<a href=\"#v:substituteProd\">substituteProd</a> :: <a href=\"Data-Type-List-Edit.html#t:Substitute\" title=\"Data.Type.List.Edit\">Substitute</a> as bs x y -&gt; (f x -&gt; f y) -&gt; <a href=\"Data-Type-List-Prod.html#t:Prod\" title=\"Data.Type.List.Prod\">Prod</a> f as -&gt; <a href=\"Data-Type-List-Prod.html#t:Prod\" title=\"Data.Type.List.Prod\">Prod</a> f bs","name":"substituteProd","module":"Data.Type.List.Edit","link":"Data-Type-List-Edit.html#v:substituteProd"},{"display_html":"<a href=\"#v:shiftIndex\">shiftIndex</a> :: <a href=\"Data-Type-List-Edit.html#t:Insert\" title=\"Data.Type.List.Edit\">Insert</a> as bs x -&gt; <a href=\"../decidable-0.1.4.0/Data-Type-Universe.html#t:Index\" title=\"Data.Type.Universe\">Index</a> as y -&gt; <a href=\"../decidable-0.1.4.0/Data-Type-Universe.html#t:Index\" title=\"Data.Type.Universe\">Index</a> bs y","name":"shiftIndex","module":"Data.Type.List.Edit","link":"Data-Type-List-Edit.html#v:shiftIndex"},{"display_html":"<span class=\"keyword\">data</span> <a href=\"#t:Unshifted\">Unshifted</a> :: [k] -&gt; k -&gt; k -&gt; <a href=\"../base-4.12.0.0/Data-Kind.html#t:Type\" title=\"Data.Kind\">Type</a> <span class=\"keyword\">where</span><ul class=\"subs\"><li><a href=\"#v:GotDeleted\">GotDeleted</a> :: <a href=\"Data-Type-List-Edit.html#t:Unshifted\" title=\"Data.Type.List.Edit\">Unshifted</a> bs x x</li><li><a href=\"#v:NotDeleted\">NotDeleted</a> :: <a href=\"../decidable-0.1.4.0/Data-Type-Universe.html#t:Index\" title=\"Data.Type.Universe\">Index</a> bs y -&gt; <a href=\"Data-Type-List-Edit.html#t:Unshifted\" title=\"Data.Type.List.Edit\">Unshifted</a> bs x y</li></ul>","name":"Unshifted GotDeleted NotDeleted","module":"Data.Type.List.Edit","link":"Data-Type-List-Edit.html#t:Unshifted"},{"display_html":"<a href=\"#v:unshiftIndex\">unshiftIndex</a> :: <a href=\"Data-Type-List-Edit.html#t:Delete\" title=\"Data.Type.List.Edit\">Delete</a> as bs x -&gt; <a href=\"../decidable-0.1.4.0/Data-Type-Universe.html#t:Index\" title=\"Data.Type.Universe\">Index</a> as y -&gt; <a href=\"Data-Type-List-Edit.html#t:Unshifted\" title=\"Data.Type.List.Edit\">Unshifted</a> bs x y","name":"unshiftIndex","module":"Data.Type.List.Edit","link":"Data-Type-List-Edit.html#v:unshiftIndex"},{"display_html":"<a href=\"#v:unshiftIndex_\">unshiftIndex_</a> :: <a href=\"Data-Type-List-Edit.html#t:Delete\" title=\"Data.Type.List.Edit\">Delete</a> as bs x -&gt; <a href=\"../decidable-0.1.4.0/Data-Type-Universe.html#t:Index\" title=\"Data.Type.Universe\">Index</a> as y -&gt; <a href=\"../base-4.12.0.0/GHC-Maybe.html#t:Maybe\" title=\"GHC.Maybe\">Maybe</a> (<a href=\"../decidable-0.1.4.0/Data-Type-Universe.html#t:Index\" title=\"Data.Type.Universe\">Index</a> bs y)","name":"unshiftIndex_","module":"Data.Type.List.Edit","link":"Data-Type-List-Edit.html#v:unshiftIndex_"},{"display_html":"<span class=\"keyword\">data</span> <a href=\"#t:Reshifted\">Reshifted</a> :: [k] -&gt; k -&gt; k -&gt; k -&gt; <a href=\"../base-4.12.0.0/Data-Kind.html#t:Type\" title=\"Data.Kind\">Type</a> <span class=\"keyword\">where</span><ul class=\"subs\"><li><a href=\"#v:GotSubbed\">GotSubbed</a> :: <a href=\"../decidable-0.1.4.0/Data-Type-Universe.html#t:Index\" title=\"Data.Type.Universe\">Index</a> bs y -&gt; <a href=\"Data-Type-List-Edit.html#t:Reshifted\" title=\"Data.Type.List.Edit\">Reshifted</a> bs z y z</li><li><a href=\"#v:NotSubbed\">NotSubbed</a> :: <a href=\"../decidable-0.1.4.0/Data-Type-Universe.html#t:Index\" title=\"Data.Type.Universe\">Index</a> bs z -&gt; <a href=\"Data-Type-List-Edit.html#t:Reshifted\" title=\"Data.Type.List.Edit\">Reshifted</a> bs x y z</li></ul>","name":"Reshifted GotSubbed NotSubbed","module":"Data.Type.List.Edit","link":"Data-Type-List-Edit.html#t:Reshifted"},{"display_html":"<a href=\"#v:reshiftIndex\">reshiftIndex</a> :: <a href=\"Data-Type-List-Edit.html#t:Substitute\" title=\"Data.Type.List.Edit\">Substitute</a> as bs x y -&gt; <a href=\"../decidable-0.1.4.0/Data-Type-Universe.html#t:Index\" title=\"Data.Type.Universe\">Index</a> as z -&gt; <a href=\"Data-Type-List-Edit.html#t:Reshifted\" title=\"Data.Type.List.Edit\">Reshifted</a> bs x y z","name":"reshiftIndex","module":"Data.Type.List.Edit","link":"Data-Type-List-Edit.html#v:reshiftIndex"},{"display_html":"<a href=\"#v:reshiftIndex_\">reshiftIndex_</a> :: <a href=\"Data-Type-List-Edit.html#t:Substitute\" title=\"Data.Type.List.Edit\">Substitute</a> as bs x y -&gt; <a href=\"../decidable-0.1.4.0/Data-Type-Universe.html#t:Index\" title=\"Data.Type.Universe\">Index</a> as z -&gt; <a href=\"../base-4.12.0.0/Data-Either.html#t:Either\" title=\"Data.Either\">Either</a> (<a href=\"../decidable-0.1.4.0/Data-Type-Universe.html#t:Index\" title=\"Data.Type.Universe\">Index</a> bs y) (<a href=\"../decidable-0.1.4.0/Data-Type-Universe.html#t:Index\" title=\"Data.Type.Universe\">Index</a> bs z)","name":"reshiftIndex_","module":"Data.Type.List.Edit","link":"Data-Type-List-Edit.html#v:reshiftIndex_"},{"display_html":"<span class=\"keyword\">data</span> <a href=\"#t:Prefix\">Prefix</a> :: [k] -&gt; [k] -&gt; <a href=\"../base-4.12.0.0/Data-Kind.html#t:Type\" title=\"Data.Kind\">Type</a> <span class=\"keyword\">where</span><ul class=\"subs\"><li><a href=\"#v:PreZ\">PreZ</a> :: <a href=\"Data-Type-List-Sublist.html#t:Prefix\" title=\"Data.Type.List.Sublist\">Prefix</a> '[] as</li><li><a href=\"#v:PreS\">PreS</a> :: <a href=\"Data-Type-List-Sublist.html#t:Prefix\" title=\"Data.Type.List.Sublist\">Prefix</a> as bs -&gt; <a href=\"Data-Type-List-Sublist.html#t:Prefix\" title=\"Data.Type.List.Sublist\">Prefix</a> (a ': as) (a ': bs)</li></ul>","name":"Prefix PreZ PreS","module":"Data.Type.List.Sublist","link":"Data-Type-List-Sublist.html#t:Prefix"},{"display_html":"<span class=\"keyword\">data</span> <a href=\"#t:Suffix\">Suffix</a> :: [k] -&gt; [k] -&gt; <a href=\"../base-4.12.0.0/Data-Kind.html#t:Type\" title=\"Data.Kind\">Type</a> <span class=\"keyword\">where</span><ul class=\"subs\"><li><a href=\"#v:SufZ\">SufZ</a> :: <a href=\"Data-Type-List-Sublist.html#t:Suffix\" title=\"Data.Type.List.Sublist\">Suffix</a> as as</li><li><a href=\"#v:SufS\">SufS</a> :: <a href=\"Data-Type-List-Sublist.html#t:Suffix\" title=\"Data.Type.List.Sublist\">Suffix</a> as bs -&gt; <a href=\"Data-Type-List-Sublist.html#t:Suffix\" title=\"Data.Type.List.Sublist\">Suffix</a> as (b ': bs)</li></ul>","name":"Suffix SufZ SufS","module":"Data.Type.List.Sublist","link":"Data-Type-List-Sublist.html#t:Suffix"},{"display_html":"<a href=\"#v:takeProd\">takeProd</a> :: <a href=\"Data-Type-List-Sublist.html#t:Prefix\" title=\"Data.Type.List.Sublist\">Prefix</a> as bs -&gt; <a href=\"Data-Type-List-Prod.html#t:Prod\" title=\"Data.Type.List.Prod\">Prod</a> f bs -&gt; <a href=\"Data-Type-List-Prod.html#t:Prod\" title=\"Data.Type.List.Prod\">Prod</a> f as","name":"takeProd","module":"Data.Type.List.Sublist","link":"Data-Type-List-Sublist.html#v:takeProd"},{"display_html":"<a href=\"#v:dropProd\">dropProd</a> :: <a href=\"Data-Type-List-Sublist.html#t:Suffix\" title=\"Data.Type.List.Sublist\">Suffix</a> as bs -&gt; <a href=\"Data-Type-List-Prod.html#t:Prod\" title=\"Data.Type.List.Prod\">Prod</a> f bs -&gt; <a href=\"Data-Type-List-Prod.html#t:Prod\" title=\"Data.Type.List.Prod\">Prod</a> f as","name":"dropProd","module":"Data.Type.List.Sublist","link":"Data-Type-List-Sublist.html#v:dropProd"},{"display_html":"<a href=\"#v:prefixLens\">prefixLens</a> :: <span class=\"keyword\">forall</span> as bs g f. <a href=\"../base-4.12.0.0/Data-Functor.html#t:Functor\" title=\"Data.Functor\">Functor</a> f =&gt; <a href=\"Data-Type-List-Sublist.html#t:Prefix\" title=\"Data.Type.List.Sublist\">Prefix</a> as bs -&gt; (<a href=\"Data-Type-List-Prod.html#t:Prod\" title=\"Data.Type.List.Prod\">Prod</a> g as -&gt; f (<a href=\"Data-Type-List-Prod.html#t:Prod\" title=\"Data.Type.List.Prod\">Prod</a> g as)) -&gt; <a href=\"Data-Type-List-Prod.html#t:Prod\" title=\"Data.Type.List.Prod\">Prod</a> g bs -&gt; f (<a href=\"Data-Type-List-Prod.html#t:Prod\" title=\"Data.Type.List.Prod\">Prod</a> g bs)","name":"prefixLens","module":"Data.Type.List.Sublist","link":"Data-Type-List-Sublist.html#v:prefixLens"},{"display_html":"<a href=\"#v:suffixLens\">suffixLens</a> :: <span class=\"keyword\">forall</span> as bs g f. <a href=\"../base-4.12.0.0/Data-Functor.html#t:Functor\" title=\"Data.Functor\">Functor</a> f =&gt; <a href=\"Data-Type-List-Sublist.html#t:Suffix\" title=\"Data.Type.List.Sublist\">Suffix</a> as bs -&gt; (<a href=\"Data-Type-List-Prod.html#t:Prod\" title=\"Data.Type.List.Prod\">Prod</a> g as -&gt; f (<a href=\"Data-Type-List-Prod.html#t:Prod\" title=\"Data.Type.List.Prod\">Prod</a> g as)) -&gt; <a href=\"Data-Type-List-Prod.html#t:Prod\" title=\"Data.Type.List.Prod\">Prod</a> g bs -&gt; f (<a href=\"Data-Type-List-Prod.html#t:Prod\" title=\"Data.Type.List.Prod\">Prod</a> g bs)","name":"suffixLens","module":"Data.Type.List.Sublist","link":"Data-Type-List-Sublist.html#v:suffixLens"},{"display_html":"<span class=\"keyword\">data</span> <a href=\"#t:Append\">Append</a> :: [k] -&gt; [k] -&gt; [k] -&gt; <a href=\"../base-4.12.0.0/Data-Kind.html#t:Type\" title=\"Data.Kind\">Type</a> <span class=\"keyword\">where</span><ul class=\"subs\"><li><a href=\"#v:AppZ\">AppZ</a> :: <a href=\"Data-Type-List-Sublist.html#t:Append\" title=\"Data.Type.List.Sublist\">Append</a> '[] as as</li><li><a href=\"#v:AppS\">AppS</a> :: <a href=\"Data-Type-List-Sublist.html#t:Append\" title=\"Data.Type.List.Sublist\">Append</a> as bs cs -&gt; <a href=\"Data-Type-List-Sublist.html#t:Append\" title=\"Data.Type.List.Sublist\">Append</a> (a ': as) bs (a ': cs)</li></ul>","name":"Append AppZ AppS","module":"Data.Type.List.Sublist","link":"Data-Type-List-Sublist.html#t:Append"},{"display_html":"<a href=\"#v:splitProd\">splitProd</a> :: <a href=\"Data-Type-List-Sublist.html#t:Append\" title=\"Data.Type.List.Sublist\">Append</a> as bs cs -&gt; <a href=\"Data-Type-List-Prod.html#t:Prod\" title=\"Data.Type.List.Prod\">Prod</a> f cs -&gt; (<a href=\"Data-Type-List-Prod.html#t:Prod\" title=\"Data.Type.List.Prod\">Prod</a> f as, <a href=\"Data-Type-List-Prod.html#t:Prod\" title=\"Data.Type.List.Prod\">Prod</a> f bs)","name":"splitProd","module":"Data.Type.List.Sublist","link":"Data-Type-List-Sublist.html#v:splitProd"},{"display_html":"<a href=\"#v:appendProd\">appendProd</a> :: <a href=\"Data-Type-List-Sublist.html#t:Append\" title=\"Data.Type.List.Sublist\">Append</a> as bs cs -&gt; <a href=\"Data-Type-List-Prod.html#t:Prod\" title=\"Data.Type.List.Prod\">Prod</a> f as -&gt; <a href=\"Data-Type-List-Prod.html#t:Prod\" title=\"Data.Type.List.Prod\">Prod</a> f bs -&gt; <a href=\"Data-Type-List-Prod.html#t:Prod\" title=\"Data.Type.List.Prod\">Prod</a> f cs","name":"appendProd","module":"Data.Type.List.Sublist","link":"Data-Type-List-Sublist.html#v:appendProd"},{"display_html":"<a href=\"#v:splitProdIso\">splitProdIso</a> :: (<a href=\"../profunctors-5.3/Data-Profunctor-Unsafe.html#t:Profunctor\" title=\"Data.Profunctor.Unsafe\">Profunctor</a> p, <a href=\"../base-4.12.0.0/Data-Functor.html#t:Functor\" title=\"Data.Functor\">Functor</a> f) =&gt; <a href=\"Data-Type-List-Sublist.html#t:Append\" title=\"Data.Type.List.Sublist\">Append</a> as bs cs -&gt; p (<a href=\"Data-Type-List-Prod.html#t:Prod\" title=\"Data.Type.List.Prod\">Prod</a> g as, <a href=\"Data-Type-List-Prod.html#t:Prod\" title=\"Data.Type.List.Prod\">Prod</a> g bs) (f (<a href=\"Data-Type-List-Prod.html#t:Prod\" title=\"Data.Type.List.Prod\">Prod</a> g as, <a href=\"Data-Type-List-Prod.html#t:Prod\" title=\"Data.Type.List.Prod\">Prod</a> g bs)) -&gt; p (<a href=\"Data-Type-List-Prod.html#t:Prod\" title=\"Data.Type.List.Prod\">Prod</a> g cs) (f (<a href=\"Data-Type-List-Prod.html#t:Prod\" title=\"Data.Type.List.Prod\">Prod</a> g cs))","name":"splitProdIso","module":"Data.Type.List.Sublist","link":"Data-Type-List-Sublist.html#v:splitProdIso"},{"display_html":"<a href=\"#v:prefixToAppend\">prefixToAppend</a> :: <a href=\"Data-Type-List-Sublist.html#t:Prefix\" title=\"Data.Type.List.Sublist\">Prefix</a> as cs -&gt; (<span class=\"keyword\">forall</span> bs. <a href=\"Data-Type-List-Sublist.html#t:Append\" title=\"Data.Type.List.Sublist\">Append</a> as bs cs -&gt; r) -&gt; r","name":"prefixToAppend","module":"Data.Type.List.Sublist","link":"Data-Type-List-Sublist.html#v:prefixToAppend"},{"display_html":"<a href=\"#v:suffixToAppend\">suffixToAppend</a> :: <a href=\"Data-Type-List-Sublist.html#t:Suffix\" title=\"Data.Type.List.Sublist\">Suffix</a> bs cs -&gt; (<span class=\"keyword\">forall</span> as. <a href=\"Data-Type-List-Sublist.html#t:Append\" title=\"Data.Type.List.Sublist\">Append</a> as bs cs -&gt; r) -&gt; r","name":"suffixToAppend","module":"Data.Type.List.Sublist","link":"Data-Type-List-Sublist.html#v:suffixToAppend"},{"display_html":"<a href=\"#v:splitAppend\">splitAppend</a> :: <a href=\"Data-Type-List-Sublist.html#t:Append\" title=\"Data.Type.List.Sublist\">Append</a> as bs cs -&gt; (<a href=\"Data-Type-List-Sublist.html#t:Prefix\" title=\"Data.Type.List.Sublist\">Prefix</a> as cs, <a href=\"Data-Type-List-Sublist.html#t:Suffix\" title=\"Data.Type.List.Sublist\">Suffix</a> bs cs)","name":"splitAppend","module":"Data.Type.List.Sublist","link":"Data-Type-List-Sublist.html#v:splitAppend"}]